pymodaq_plugins_tango/__init__.py
pymodaq_plugins_tango/utils.py
pymodaq_plugins_tango/app/__init__.py
pymodaq_plugins_tango/app/custom_app_tango.py
pymodaq_plugins_tango/daq_move_plugins/__init__.py
pymodaq_plugins_tango/daq_viewer_plugins/__init__.py
pymodaq_plugins_tango/daq_viewer_plugins/plugins_0D/__init__.py
pymodaq_plugins_tango/daq_viewer_plugins/plugins_0D/daq_0Dviewer_Energy.py
pymodaq_plugins_tango/daq_viewer_plugins/plugins_1D/__init__.py
pymodaq_plugins_tango/daq_viewer_plugins/plugins_1D/daq_1Dviewer_TangoSpectrometer.py
pymodaq_plugins_tango/daq_viewer_plugins/plugins_2D/__init__.py
pymodaq_plugins_tango/daq_viewer_plugins/plugins_2D/daq_2Dviewer_TangoCamera.py
pymodaq_plugins_tango/daq_viewer_plugins/plugins_ND/__init__.py
pymodaq_plugins_tango/daq_viewer_plugins/plugins_ND/daq_NDviewer_MockEvents.py
pymodaq_plugins_tango/daq_viewer_plugins_old/__init__.py
pymodaq_plugins_tango/daq_viewer_plugins_old/plugins_0D/__init__.py
pymodaq_plugins_tango/daq_viewer_plugins_old/plugins_1D/__init__.py
pymodaq_plugins_tango/daq_viewer_plugins_old/plugins_1D/daq_1Dviewer_TangoSpectrometer.py
pymodaq_plugins_tango/daq_viewer_plugins_old/plugins_2D/__init__.py
pymodaq_plugins_tango/exporters/__init__.py
pymodaq_plugins_tango/extensions/__init__.py
pymodaq_plugins_tango/extensions/custom_extension_tango.py
pymodaq_plugins_tango/hardware/__init__.py
pymodaq_plugins_tango/hardware/TANGO/__init__.py
pymodaq_plugins_tango/hardware/TANGO/tango_config.py
pymodaq_plugins_tango/hardware/TANGO/tango_device.py
pymodaq_plugins_tango/models/__init__.py
pymodaq_plugins_tango/resources/VERSION
pymodaq_plugins_tango/resources/__init__.py
pymodaq_plugins_tango/resources/config_tango.toml
pymodaq_plugins_tango/resources/tango_devices.toml
pymodaq_plugins_tango/scanners/__init__.py
pymodaq_plugins_tango-1.0.20.dist-info/LICENSE
pymodaq_plugins_tango-1.0.20.dist-info/METADATA
pymodaq_plugins_tango-1.0.20.dist-info/WHEEL
pymodaq_plugins_tango-1.0.20.dist-info/entry_points.txt
pymodaq_plugins_tango-1.0.20.dist-info/top_level.txt
pymodaq_plugins_tango-1.0.20.dist-info/RECORD
