Metadata-Version: 2.1
Name: pymodaq-plugins-tango
Version: 1.0.20
Summary: some word about your plugin
Home-page: https://github.com/PyMoDAQ-LOA/pymodaq_plugins_tango
Author: Aline Vernier
Author-email: aline.vernier@polytechnique.edu
License: MIT
Classifier: Programming Language :: Python :: 3
Classifier: Development Status :: 5 - Production/Stable
Classifier: Environment :: Other Environment
Classifier: Intended Audience :: Science/Research
Classifier: Topic :: Scientific/Engineering :: Human Machine Interfaces
Classifier: Topic :: Scientific/Engineering :: Visualization
Classifier: License :: OSI Approved :: MIT License
Classifier: Operating System :: OS Independent
Classifier: Topic :: Software Development :: Libraries :: Python Modules
Classifier: Topic :: Software Development :: User Interfaces
License-File: LICENSE
Requires-Dist: toml
Requires-Dist: pymodaq>=4.3.6
